<?xml version="1.0" encoding="utf-8"?>
<key id="ae12c3fc-c379-4cf7-af70-7ad26c82176c" version="1">
  <creationDate>2025-11-15T03:22:58.7474981Z</creationDate>
  <activationDate>2025-11-15T03:22:58.7474981Z</activationDate>
  <expirationDate>2026-02-13T03:22:58.7474981Z</expirationDate>
  <descriptor deserializerType="Microsoft.AspNetCore.DataProtection.AuthenticatedEncryption.ConfigurationModel.AuthenticatedEncryptorDescriptorDeserializer, Microsoft.AspNetCore.DataProtection, Version=9.0.0.0, Culture=neutral, PublicKeyToken=adb9793829ddae60">
    <descriptor>
      <encryption algorithm="AES_256_CBC" />
      <validation algorithm="HMACSHA256" />
      <masterKey p4:requiresEncryption="true" xmlns:p4="http://schemas.asp.net/2015/03/dataProtection">
        <!-- Warning: the key below is in an unencrypted form. -->
        <value>LJvVGXzeoBN2vx923ZJf07ce6ckZCycKV/c3PCO+ZrHVRlOEqSHfpoypzNd8626WyFNYV6pR5ulyT8f39L98jg==</value>
      </masterKey>
    </descriptor>
  </descriptor>
</key>